refsig
