Metadata-Version: 1.0
Name: refsig
Version: 1.0.5
Summary: Package for obtaining the referential signal from a set of iEEG data
Home-page: https://github.com/DandaPanda/refsig
Author: Daniel Uher in affiliation with FNUSA-ICRC Brno and BUT Brno
Author-email: daniel-uher@hotmail.com
License: MIT
Keywords: reference iEEG EEG referential signal ICA
Platform: UNKNOWN
